cosyvoice/__init__.py
cosyvoice/bin/average_model.py
cosyvoice/bin/export_jit.py
cosyvoice/bin/export_onnx.py
cosyvoice/bin/inference_deprecated.py
cosyvoice/bin/select_best_checkpoint.py
cosyvoice/bin/train.py
cosyvoice/bin/upload_weights.py
cosyvoice/cli/__init__.py
cosyvoice/cli/cosyvoice.py
cosyvoice/cli/frontend.py
cosyvoice/cli/model.py
cosyvoice/dataset/__init__.py
cosyvoice/dataset/dataset.py
cosyvoice/dataset/processor.py
cosyvoice/flow/decoder.py
cosyvoice/flow/flow.py
cosyvoice/flow/flow_matching.py
cosyvoice/flow/length_regulator.py
cosyvoice/hifigan/discriminator.py
cosyvoice/hifigan/f0_predictor.py
cosyvoice/hifigan/generator.py
cosyvoice/hifigan/hifigan.py
cosyvoice/llm/llm.py
cosyvoice/tokenizer/tokenizer.py
cosyvoice/tokenizer/assets/multilingual_zh_ja_yue_char_del.tiktoken
cosyvoice/transformer/__init__.py
cosyvoice/transformer/activation.py
cosyvoice/transformer/attention.py
cosyvoice/transformer/convolution.py
cosyvoice/transformer/decoder.py
cosyvoice/transformer/decoder_layer.py
cosyvoice/transformer/embedding.py
cosyvoice/transformer/encoder.py
cosyvoice/transformer/encoder_layer.py
cosyvoice/transformer/label_smoothing_loss.py
cosyvoice/transformer/positionwise_feed_forward.py
cosyvoice/transformer/subsampling.py
cosyvoice/transformer/upsample_encoder.py
cosyvoice/utils/__init__.py
cosyvoice/utils/class_utils.py
cosyvoice/utils/common.py
cosyvoice/utils/executor.py
cosyvoice/utils/file_utils.py
cosyvoice/utils/frontend_utils.py
cosyvoice/utils/losses.py
cosyvoice/utils/mask.py
cosyvoice/utils/scheduler.py
cosyvoice/utils/train_utils.py
cosyvoice/vllm/cosyvoice2.py
cosyvoice2_eu/__init__.py
cosyvoice2_eu/cli.py
cosyvoice2_eu/__pycache__/__init__.cpython-310.pyc
cosyvoice2_eu/__pycache__/__init__.cpython-313.pyc
cosyvoice2_eu/__pycache__/cli.cpython-310.pyc
cosyvoice2_eu/__pycache__/cli.cpython-313.pyc
cosyvoice2_eu-0.2.8.data/data/LICENSE
cosyvoice2_eu-0.2.8.data/data/NOTICE
cosyvoice2_eu-0.2.8.data/data/README.md
cosyvoice2_eu-0.2.8.dist-info/licenses/LICENSE
cosyvoice2_eu-0.2.8.dist-info/licenses/NOTICE
cosyvoice2_eu-0.2.8.dist-info/METADATA
cosyvoice2_eu-0.2.8.dist-info/WHEEL
cosyvoice2_eu-0.2.8.dist-info/entry_points.txt
cosyvoice2_eu-0.2.8.dist-info/top_level.txt
cosyvoice2_eu-0.2.8.dist-info/RECORD
